rlportfolio/algorithm/__init__.py
rlportfolio/algorithm/episodic_policy_gradient.py
rlportfolio/algorithm/fast_policy_gradient.py
rlportfolio/algorithm/policy_gradient.py
rlportfolio/algorithm/buffers/__init__.py
rlportfolio/algorithm/buffers/portfolio_vector_memory.py
rlportfolio/algorithm/buffers/replay_buffers.py
rlportfolio/data/__init__.py
rlportfolio/data/scalers.py
rlportfolio/environment/__init__.py
rlportfolio/environment/portfolio_optimization_env.py
rlportfolio/policy/__init__.py
rlportfolio/policy/ei3.py
rlportfolio/policy/eiie.py
rlportfolio/policy/gpm.py
rlportfolio/utils/__init__.py
rlportfolio/utils/general.py
rlportfolio-0.3.0.dist-info/LICENSE
rlportfolio-0.3.0.dist-info/METADATA
rlportfolio-0.3.0.dist-info/WHEEL
rlportfolio-0.3.0.dist-info/top_level.txt
rlportfolio-0.3.0.dist-info/RECORD
