Metadata-Version: 2.2
Name: rlportfolio
Version: 0.3.0
Summary: Reinforcement learning framework for portfolio optimization tasks.
Author-email: Caio de Souza Barbosa Costa <csbc326@gmail.com>
Maintainer-email: Caio de Souza Barbosa Costa <csbc326@gmail.com>
License: The MIT License (MIT)
Project-URL: Documentation, https://rlportfolio.readthedocs.io/en/latest/
Project-URL: Homepage, https://github.com/CaioSBC/RLPortfolio
Project-URL: Issues, https://github.com/CaioSBC/RLPortfolio/issues
Keywords: deep-learning,reinforcement-learning,pytorch,finance,portfolio-optimization,portfolio-management,asset-allocation
Classifier: Development Status :: 3 - Alpha
Classifier: Intended Audience :: Science/Research
Classifier: Intended Audience :: Financial and Insurance Industry
Classifier: License :: OSI Approved :: MIT License
Classifier: Natural Language :: English
Classifier: Programming Language :: Python :: 3
Classifier: Operating System :: MacOS
Classifier: Operating System :: POSIX :: Linux
Classifier: Operating System :: Microsoft :: Windows
Classifier: Topic :: Scientific/Engineering :: Artificial Intelligence
Classifier: Topic :: Office/Business :: Financial :: Investment
Requires-Python: >=3.9
License-File: LICENSE
Requires-Dist: gymnasium
Requires-Dist: jupyter
Requires-Dist: numpy
Requires-Dist: pandas
Requires-Dist: pytest
Requires-Dist: quantstats
Requires-Dist: scikit-learn
Requires-Dist: tensorboard
Requires-Dist: torch
Requires-Dist: torch_geometric
Requires-Dist: tqdm
Provides-Extra: test
Requires-Dist: pytest; extra == "test"
Requires-Dist: sphinx; extra == "test"
Requires-Dist: sphinx-rtd-theme; extra == "test"
